keras_tools/__init__.py
keras_tools/configuration_performer_attention.py
keras_tools/convenience_operations.py
keras_tools/convergence_metric.py
keras_tools/expose_latent.py
keras_tools/huggingface_tools.py
keras_tools/learning_rate_schedules.py
keras_tools/lm_preprocessing.py
keras_tools/memory_callback.py
keras_tools/model_checkpoint.py
keras_tools/modeling_tf_performer_attention.py
keras_tools/naswt.py
keras_tools/noise_curriculum.py
keras_tools/plot_tools.py
keras_tools/reinitialize.py
keras_tools/silence_tensorflow.py
keras_tools/test_sg_shapes.py
keras_tools/esoteric_activations/__init__.py
keras_tools/esoteric_activations/smoothrelus.py
keras_tools/esoteric_callbacks/__init__.py
keras_tools/esoteric_callbacks/annealing_callback.py
keras_tools/esoteric_callbacks/clear_memory.py
keras_tools/esoteric_callbacks/clr_callback.py
keras_tools/esoteric_callbacks/earlystop_byvalue.py
keras_tools/esoteric_callbacks/gradient_tensorboard.py
keras_tools/esoteric_callbacks/loggers.py
keras_tools/esoteric_callbacks/lr_finder.py
keras_tools/esoteric_callbacks/several_validations.py
keras_tools/esoteric_callbacks/time_stopping.py
keras_tools/esoteric_initializers/__init__.py
keras_tools/esoteric_initializers/extra_variance_criticality.py
keras_tools/esoteric_initializers/func_on_initializer.py
keras_tools/esoteric_initializers/out_initializer.py
keras_tools/esoteric_layers/FiLM_layer_variations.py
keras_tools/esoteric_layers/__init__.py
keras_tools/esoteric_layers/add_loss_layer.py
keras_tools/esoteric_layers/add_metrics_layer.py
keras_tools/esoteric_layers/close_graph.py
keras_tools/esoteric_layers/combine_tensors.py
keras_tools/esoteric_layers/contrastive_loss_language.py
keras_tools/esoteric_layers/convenience_layers.py
keras_tools/esoteric_layers/cyclic_dropout.py
keras_tools/esoteric_layers/dropin.py
keras_tools/esoteric_layers/dropword.py
keras_tools/esoteric_layers/factorized_dense.py
keras_tools/esoteric_layers/gumbel_layers.py
pyaromatics-0.0.2.dist-info/LICENSE
pyaromatics-0.0.2.dist-info/METADATA
pyaromatics-0.0.2.dist-info/WHEEL
pyaromatics-0.0.2.dist-info/top_level.txt
pyaromatics-0.0.2.dist-info/RECORD
