Metadata-Version: 2.1
Name: pyaromatics
Version: 0.0.2
Summary: Testing installation of Package
Home-page: https://github.com/lucehe/pyaromatics
Author: Luca Herrtti
Author-email: luca.herrtti@gmail.com
License: MIT
Project-URL: Bug Tracker, https://github.com/lucehe/pyaromatics/issues
Classifier: Development Status :: 3 - Alpha
Classifier: Programming Language :: Python :: 3 :: Only
Classifier: License :: OSI Approved :: MIT License
Classifier: Operating System :: OS Independent
Requires-Python: >=3.6
License-File: LICENSE
